apsisnet/__init__.py
apsisnet/apsisnet.py
apsisnet/modules.py
apsisnet/utils.py
apsisnet-0.0.2.dist-info/METADATA
apsisnet-0.0.2.dist-info/WHEEL
apsisnet-0.0.2.dist-info/top_level.txt
apsisnet-0.0.2.dist-info/RECORD
