Metadata-Version: 2.1
Name: apsisnet
Version: 0.0.2
Summary: Bangla Languge Recognizer Toolkit
Home-page: https://github.com/mnansary/apsisnet.git
Author: Nazmuddoha Ansary
Author-email: nazmuddoha.ansary@apsissolutions.com
License: MIT
Keywords: ocr,scene ocr,apsisnet
Classifier: Development Status :: 3 - Alpha
Classifier: Intended Audience :: Education
Classifier: Operating System :: POSIX :: Linux
Classifier: License :: OSI Approved :: MIT License
Classifier: Programming Language :: Python :: 3
Requires-Dist: numpy
Requires-Dist: matplotlib
Requires-Dist: opencv-python
Requires-Dist: pandas
Requires-Dist: tqdm
Requires-Dist: termcolor
Requires-Dist: gdown
Requires-Dist: bnunicodenormalizer
Requires-Dist: onnxruntime-gpu ==1.16.0
